mr23013uno/__init__.py
mr23013uno/lineales.py
mr23013uno/no_lineales.py
mr23013uno-0.1.dist-info/licenses/LICENSE
mr23013uno-0.1.dist-info/METADATA
mr23013uno-0.1.dist-info/WHEEL
mr23013uno-0.1.dist-info/top_level.txt
mr23013uno-0.1.dist-info/RECORD
